odoo/addons/l10n_ro_account_edit_currency_rate/README.rst
odoo/addons/l10n_ro_account_edit_currency_rate/__init__.py
odoo/addons/l10n_ro_account_edit_currency_rate/__manifest__.py
odoo/addons/l10n_ro_account_edit_currency_rate/i18n/l10n_ro_account_edit_currency_rate.pot
odoo/addons/l10n_ro_account_edit_currency_rate/i18n/ro.po
odoo/addons/l10n_ro_account_edit_currency_rate/models/__init__.py
odoo/addons/l10n_ro_account_edit_currency_rate/models/account_move.py
odoo/addons/l10n_ro_account_edit_currency_rate/readme/CONTRIBUTORS.rst
odoo/addons/l10n_ro_account_edit_currency_rate/readme/DESCRIPTION.rst
odoo/addons/l10n_ro_account_edit_currency_rate/readme/INSTALL.rst
odoo/addons/l10n_ro_account_edit_currency_rate/static/description/icon.png
odoo/addons/l10n_ro_account_edit_currency_rate/static/description/index.html
odoo/addons/l10n_ro_account_edit_currency_rate/tests/__init__.py
odoo/addons/l10n_ro_account_edit_currency_rate/tests/test_edit_currency_rate.py
odoo14_addon_l10n_ro_account_edit_currency_rate-14.0.3.3.0.dist-info/METADATA
odoo14_addon_l10n_ro_account_edit_currency_rate-14.0.3.3.0.dist-info/WHEEL
odoo14_addon_l10n_ro_account_edit_currency_rate-14.0.3.3.0.dist-info/top_level.txt
odoo14_addon_l10n_ro_account_edit_currency_rate-14.0.3.3.0.dist-info/RECORD
